setup.py
kcwhttp/__init__.py
kcwhttp/httpclass.py
kcwhttp.egg-info/PKG-INFO
kcwhttp.egg-info/SOURCES.txt
kcwhttp.egg-info/dependency_links.txt
kcwhttp.egg-info/requires.txt
kcwhttp.egg-info/top_level.txt
kcwhttp/selenium3/__init__.py
kcwhttp/selenium3/common/__init__.py
kcwhttp/selenium3/common/exceptions.py
kcwhttp/selenium3/webdriver/__init__.py
kcwhttp/selenium3/webdriver/android/__init__.py
kcwhttp/selenium3/webdriver/android/webdriver.py
kcwhttp/selenium3/webdriver/blackberry/__init__.py
kcwhttp/selenium3/webdriver/blackberry/webdriver.py
kcwhttp/selenium3/webdriver/chrome/__init__.py
kcwhttp/selenium3/webdriver/chrome/options.py
kcwhttp/selenium3/webdriver/chrome/remote_connection.py
kcwhttp/selenium3/webdriver/chrome/service.py
kcwhttp/selenium3/webdriver/chrome/webdriver.py
kcwhttp/selenium3/webdriver/common/__init__.py
kcwhttp/selenium3/webdriver/common/action_chains.py
kcwhttp/selenium3/webdriver/common/alert.py
kcwhttp/selenium3/webdriver/common/by.py
kcwhttp/selenium3/webdriver/common/desired_capabilities.py
kcwhttp/selenium3/webdriver/common/keys.py
kcwhttp/selenium3/webdriver/common/proxy.py
kcwhttp/selenium3/webdriver/common/service.py
kcwhttp/selenium3/webdriver/common/touch_actions.py
kcwhttp/selenium3/webdriver/common/utils.py
kcwhttp/selenium3/webdriver/common/html5/__init__.py
kcwhttp/selenium3/webdriver/common/html5/application_cache.py
kcwhttp/selenium3/webdriver/edge/__init__.py
kcwhttp/selenium3/webdriver/edge/options.py
kcwhttp/selenium3/webdriver/edge/service.py
kcwhttp/selenium3/webdriver/edge/webdriver.py
kcwhttp/selenium3/webdriver/firefox/__init__.py
kcwhttp/selenium3/webdriver/firefox/extension_connection.py
kcwhttp/selenium3/webdriver/firefox/firefox_binary.py
kcwhttp/selenium3/webdriver/firefox/firefox_profile.py
kcwhttp/selenium3/webdriver/firefox/options.py
kcwhttp/selenium3/webdriver/firefox/remote_connection.py
kcwhttp/selenium3/webdriver/firefox/service.py
kcwhttp/selenium3/webdriver/firefox/webdriver.py
kcwhttp/selenium3/webdriver/firefox/webelement.py
kcwhttp/selenium3/webdriver/ie/__init__.py
kcwhttp/selenium3/webdriver/ie/service.py
