Metadata-Version: 1.2
Name: kcwhttp
Version: 3.34
Summary: kcwhttp
Home-page: UNKNOWN
Author: 百里
Author-email: kcwebs@kwebapp.cn
Maintainer: 坤坤
Maintainer-email: fk1402936534@qq.com
License: MIT License
Keywords: kcwhttp3.34
Platform: UNKNOWN
